pyproject.toml
setup.cfg
setup.py
librusapi/__init__.py
librusapi/exceptions.py
librusapi/helpers.py
librusapi/messages.py
librusapi/timetable.py
librusapi/token.py
librusapi/urls.py
librusapi.egg-info/PKG-INFO
librusapi.egg-info/SOURCES.txt
librusapi.egg-info/dependency_links.txt
librusapi.egg-info/requires.txt
librusapi.egg-info/top_level.txt