Metadata-Version: 1.1
Name: librusapi
Version: 0.0.5
Summary: Scraper for Librus Synergia
Home-page: https://github.com/ravensiris/librusapi
Author: Maksymilian Jodłowski
Author-email: UNKNOWN
License: MIT
Keywords: librus,scraper,api
Platform: UNKNOWN
Classifier: License :: OSI Approved :: MIT License
Classifier: Intended Audience :: Developers
Classifier: Programming Language :: Python :: 3
Classifier: Programming Language :: Python :: 3.9
